setup.cfg
setup.py
caafinder/__init__.py
caafinder/database.py
caafinder/workspace.py
demo_wmy_meta.egg-info/PKG-INFO
demo_wmy_meta.egg-info/SOURCES.txt
demo_wmy_meta.egg-info/dependency_links.txt
demo_wmy_meta.egg-info/top_level.txt