Metadata-Version: 2.1
Name: demo-wmy-meta
Version: 0.1.5
Summary: 手写python库
Home-page: https://github.com/UpMing19/python_library
Author: mingyu.wang
Author-email: mingyu.wang@appshahe.com
License: MIT License
Keywords: MetaApp
Platform: any
